<?xml version="1.0" encoding="UTF-8"?>
<restaurants>
    <restaurant id="1" name="The Olive Tree">
        <address>27 Marshall Street, Edinburgh, EH8 9BJ</address>
        <cuisine>Mediterranean</cuisine>
        <phoneno>0131 667 9997</phoneno>
        <feedback>3.2</feedback>
        <nyitvatartas>8:00-16:00;8:00-16:00;8:00-16:00;8:00-16:00;8:00-16:00;9:00-13:00;-</nyitvatartas>
    </restaurant>
    <restaurant id="2" name="Nawroz">
        <address>26 Potterow, Edinburgh, EH8 9BT</address>
        <cuisine>Kurdish</cuisine>
        <phoneno>0131 667 2299</phoneno>
        <feedback>4.5</feedback>
        <nyitvatartas>12:00-20:00;12:00-20:00;12:00-20:00;12:00-20:00;12:00-20:00;-;-</nyitvatartas>
    </restaurant>
    <restaurant id="3" name="Kebab Mahal">
        <address>7 Nicolson Square, Edinburgh, EH8 9BH</address>
        <cuisine>Indian</cuisine>
        <phoneno>0131 622 7228</phoneno>
        <feedback>4.2</feedback>
        <nyitvatartas>12:00-22:00;12:00-22:00;12:00-22:00;12:00-22:00;12:00-20:00;12:00-20:00;-</nyitvatartas>
    </restaurant>
    <restaurant id="4" name="Sylvesters">
        <address>55 West Nicolson Street, Edinburgh, EH8 9DB</address>
        <cuisine>Scottish</cuisine>
        <phoneno>0131 662 4493</phoneno>
        <feedback>3.1</feedback>
        <nyitvatartas>-;-;12:00-22:00;12:00-22:00;12:00-20:00;12:00-20:00;12:00-20:00</nyitvatartas>
    </restaurant>
    <restaurant id="5" name="Buffalo Grill">
        <address>12 Chapel Street, Edinburgh, EH8 9AY</address>
        <cuisine>North American</cuisine>
        <phoneno>0131 667 7427</phoneno>
        <feedback>4.9</feedback>
        <nyitvatartas>-;-;12:00-22:00;12:00-22:00;12:00-20:00;12:00-20:00;12:00-20:00</nyitvatartas>
    </restaurant>
    <restaurant id="6" name="Nile Valley">
        <address>6 Chapel Street, Edinburgh, EH8 9AY</address>
        <cuisine>Cafe</cuisine>
        <phoneno>0131 667 8200</phoneno>
        <feedback>4.4</feedback>
        <nyitvatartas>-;-;12:00-22:00;-;12:00-20:00;12:00-20:00;12:00-20:00</nyitvatartas>
    </restaurant>
    <restaurant id="7" name="Kalpna">
        <address>2 St Patrick's Square, Edinburgh, EH8 9EZ</address>
        <cuisine>Indian</cuisine>
        <phoneno>0131 667 9890</phoneno>
        <feedback>5</feedback>
        <nyitvatartas>12:00-22:00;12:00-22:00;12:00-22:00;12:00-22:00;12:00-20:00;12:00-20:00;12:00-20:00</nyitvatartas>
    </restaurant>
    <restaurant id="8" name="Suruchi">
        <address>14A Nicholson Street</address>
        <cuisine>Indian</cuisine>
        <phoneno>0131 556 6583</phoneno>
        <feedback>4.8</feedback>
        <nyitvatartas>-;12:00-22:00;-;12:00-22:00;12:00-20:00;12:00-20:00;12:00-20:00</nyitvatartas>
    </restaurant>
    <restaurant id="9" name="Ciao Roma">
        <address>64 South Bridge</address>
        <cuisine>Italian</cuisine>
        <phoneno>0131 557 3777</phoneno>
        <feedback>3.6</feedback>
        <nyitvatartas>12:00-22:00;12:00-22:00;12:00-22:00;12:00-22:00;12:00-20:00;12:00-20:00;-</nyitvatartas>
    </restaurant>
    <restaurant id="10" name="Ti Amo">
        <address>16 Nicolson Street, Old Town, Edinburgh, EH8 9DH</address>
        <cuisine>Italian</cuisine>
        <phoneno>0131 556 5678</phoneno>
        <feedback>4.1</feedback>
        <nyitvatartas>11:00-22:00;11:00-22:00;11:00-22:00;11:00-22:00;11:00-20:00;11:00-20:00;11:00-20:00</nyitvatartas>
    </restaurant>
</restaurants>
